mpl_richtext/__init__.py
mpl_richtext/core.py
mpl_richtext/shaping.py
mpl_richtext/version.py
mpl_richtext-0.1.7.dist-info/licenses/LICENSE
mpl_richtext-0.1.7.dist-info/METADATA
mpl_richtext-0.1.7.dist-info/WHEEL
mpl_richtext-0.1.7.dist-info/top_level.txt
mpl_richtext-0.1.7.dist-info/RECORD
