Metadata-Version: 2.4
Name: mpl-richtext
Version: 0.1.7
Summary: Rich text rendering for Matplotlib with multi-color and multi-style support
Home-page: https://github.com/ra8in/mpl-richtext
Author: Rabin Katel
Author-email: Rabin Katel <kattelrabinraja13@gmail.com>
License: MIT
Project-URL: Homepage, https://github.com/ra8in/mpl-richtext
Project-URL: Documentation, https://github.com/ra8in/mpl-richtext#readme
Project-URL: Repository, https://github.com/ra8in/mpl-richtext
Project-URL: Bug Tracker, https://github.com/ra8in/mpl-richtext/issues
Keywords: matplotlib,text,color,rich-text,multi-color,visualization,plotting
Classifier: Development Status :: 3 - Alpha
Classifier: Intended Audience :: Developers
Classifier: Intended Audience :: Science/Research
Classifier: Topic :: Scientific/Engineering :: Visualization
Classifier: License :: OSI Approved :: MIT License
Classifier: Programming Language :: Python :: 3
Classifier: Programming Language :: Python :: 3.8
Classifier: Programming Language :: Python :: 3.9
Classifier: Programming Language :: Python :: 3.10
Classifier: Programming Language :: Python :: 3.11
Classifier: Programming Language :: Python :: 3.12
Classifier: Operating System :: OS Independent
Requires-Python: >=3.8
License-File: LICENSE
Requires-Dist: matplotlib>=3.5.0
Requires-Dist: uharfbuzz>=0.30.0
Requires-Dist: fonttools>=4.34.0
Provides-Extra: dev
Requires-Dist: pytest>=7.0; extra == "dev"
Requires-Dist: pytest-cov>=4.0; extra == "dev"
Requires-Dist: black>=22.0; extra == "dev"
Requires-Dist: flake8>=5.0; extra == "dev"
Requires-Dist: mypy>=0.990; extra == "dev"
Dynamic: author
Dynamic: home-page
Dynamic: license-file
Dynamic: requires-python
